walacor_python_sdk/__init__.py
walacor_python_sdk/_version.py
walacor_python_sdk/base_service.py
walacor_python_sdk/main.py
walacor_python_sdk/sdk_facade.py
walacor_python_sdk/w_client.py
walacor_python_sdk/authentication/__init__.py
walacor_python_sdk/authentication/auth_service.py
d_walacor_python_sdk-9999.0.1.dist-info/LICENSE
d_walacor_python_sdk-9999.0.1.dist-info/METADATA
d_walacor_python_sdk-9999.0.1.dist-info/WHEEL
d_walacor_python_sdk-9999.0.1.dist-info/top_level.txt
d_walacor_python_sdk-9999.0.1.dist-info/RECORD
